{
  "anime": [
    {
      "cover": "https://cdn.jsdelivr.net/gh/czy0729/Bangumi-Static@master/data/discovery/cover/325585.jpg",
      "title": "無職転生 ～異世界行ったら本気だす～ 第2クール",
      "subjectId": "325585",
      "info": "3204人关注"
    },
    {
      "cover": "https://cdn.jsdelivr.net/gh/czy0729/Bangumi-Static@master/data/discovery/cover/348335.jpg",
      "title": "平家物語",
      "subjectId": "348335",
      "info": "1992人关注"
    },
    {
      "cover": "https://cdn.jsdelivr.net/gh/czy0729/Bangumi-Static@master/data/discovery/cover/331535.jpg",
      "title": "takt op.Destiny",
      "subjectId": "331535",
      "info": "2119人关注"
    },
    {
      "cover": "https://cdn.jsdelivr.net/gh/czy0729/Bangumi-Static@master/data/discovery/cover/335225.jpg",
      "title": "古見さんは、コミュ症です。",
      "subjectId": "335225",
      "info": "1658人关注"
    },
    {
      "cover": "https://cdn.jsdelivr.net/gh/czy0729/Bangumi-Static@master/data/discovery/cover/330973.jpg",
      "title": "見える子ちゃん",
      "subjectId": "330973",
      "info": "1394人关注"
    },
    {
      "cover": "https://cdn.jsdelivr.net/gh/czy0729/Bangumi-Static@master/data/discovery/cover/328313.jpg",
      "title": "世界最高の暗殺者、 異世界貴族に転生する",
      "subjectId": "328313",
      "info": "1339人关注"
    },
    {
      "cover": "https://cdn.jsdelivr.net/gh/czy0729/Bangumi-Static@master/data/discovery/cover/331887.jpg",
      "title": "86―エイティシックス― 第2クール",
      "subjectId": "331887",
      "info": "1371人关注"
    }
  ],
  "game": [
    {
      "cover": "https://cdn.jsdelivr.net/gh/czy0729/Bangumi-Static@master/data/discovery/cover/284097.jpg",
      "title": "テイルズ オブ アライズ",
      "subjectId": "284097",
      "info": "568人关注"
    },
    {
      "cover": "https://cdn.jsdelivr.net/gh/czy0729/Bangumi-Static@master/data/discovery/cover/162854.jpg",
      "title": "Eastward",
      "subjectId": "162854",
      "info": "205人关注"
    },
    {
      "cover": "https://cdn.jsdelivr.net/gh/czy0729/Bangumi-Static@master/data/discovery/cover/324621.jpg",
      "title": "ふゆから、くるる。",
      "subjectId": "324621",
      "info": "519人关注"
    },
    {
      "cover": "https://cdn.jsdelivr.net/gh/czy0729/Bangumi-Static@master/data/discovery/cover/295364.jpg",
      "title": "ハミダシクリエイティブ",
      "subjectId": "295364",
      "info": "917人关注"
    },
    {
      "cover": "https://cdn.jsdelivr.net/gh/czy0729/Bangumi-Static@master/data/discovery/cover/284157.jpg",
      "title": "原神",
      "subjectId": "284157",
      "info": "1199人关注"
    },
    {
      "cover": "https://cdn.jsdelivr.net/gh/czy0729/Bangumi-Static@master/data/discovery/cover/46874.jpg",
      "title": "月姫 -A piece of blue glass moon-",
      "subjectId": "46874",
      "info": "868人关注"
    },
    {
      "cover": "https://cdn.jsdelivr.net/gh/czy0729/Bangumi-Static@master/data/discovery/cover/22423.jpg",
      "title": "サクラノ詩 —櫻の森の上を舞う—",
      "subjectId": "22423",
      "info": "4709人关注"
    }
  ],
  "book": [
    {
      "cover": "https://cdn.jsdelivr.net/gh/czy0729/Bangumi-Static@master/data/discovery/cover/268279.jpg",
      "title": "チェンソーマン",
      "subjectId": "268279",
      "info": "2944人关注"
    },
    {
      "cover": "https://cdn.jsdelivr.net/gh/czy0729/Bangumi-Static@master/data/discovery/cover/217833.jpg",
      "title": "ブルーピリオド",
      "subjectId": "217833",
      "info": "419人关注"
    },
    {
      "cover": "https://cdn.jsdelivr.net/gh/czy0729/Bangumi-Static@master/data/discovery/cover/305429.jpg",
      "title": "葬送のフリーレン",
      "subjectId": "305429",
      "info": "979人关注"
    },
    {
      "cover": "https://cdn.jsdelivr.net/gh/czy0729/Bangumi-Static@master/data/discovery/cover/303186.jpg",
      "title": "【推しの子】",
      "subjectId": "303186",
      "info": "705人关注"
    },
    {
      "cover": "https://cdn.jsdelivr.net/gh/czy0729/Bangumi-Static@master/data/discovery/cover/342254.jpg",
      "title": "ルックバック",
      "subjectId": "342254",
      "info": "883人关注"
    },
    {
      "cover": "https://cdn.jsdelivr.net/gh/czy0729/Bangumi-Static@master/data/discovery/cover/135218.jpg",
      "title": "かぐや様は告らせたい～天才たちの恋愛頭脳戦～",
      "subjectId": "135218",
      "info": "1784人关注"
    },
    {
      "cover": "https://cdn.jsdelivr.net/gh/czy0729/Bangumi-Static@master/data/discovery/cover/179872.jpg",
      "title": "ファイアパンチ",
      "subjectId": "179872",
      "info": "1837人关注"
    }
  ],
  "music": [
    {
      "cover": "https://cdn.jsdelivr.net/gh/czy0729/Bangumi-Static@master/data/discovery/cover/339410.jpg",
      "title": "TV ANIMATION「Sonny Boy」soundtrack",
      "subjectId": "339410",
      "info": "54人关注"
    },
    {
      "cover": "https://cdn.jsdelivr.net/gh/czy0729/Bangumi-Static@master/data/discovery/cover/349618.jpg",
      "title": "原神-寂远无妄之国 Realm of Tranquil Eternity",
      "subjectId": "349618",
      "info": "36人关注"
    },
    {
      "cover": "https://cdn.jsdelivr.net/gh/czy0729/Bangumi-Static@master/data/discovery/cover/350215.jpg",
      "title": "タクト",
      "subjectId": "350215",
      "info": "36人关注"
    },
    {
      "cover": "https://cdn.jsdelivr.net/gh/czy0729/Bangumi-Static@master/data/discovery/cover/321924.jpg",
      "title": "One Last Kiss",
      "subjectId": "321924",
      "info": "432人关注"
    },
    {
      "cover": "https://cdn.jsdelivr.net/gh/czy0729/Bangumi-Static@master/data/discovery/cover/341443.jpg",
      "title": "星の旅人/シナヤカナミライ",
      "subjectId": "341443",
      "info": "63人关注"
    },
    {
      "cover": "https://cdn.jsdelivr.net/gh/czy0729/Bangumi-Static@master/data/discovery/cover/238923.jpg",
      "title": "Xenoblade2 Original Soundtrack",
      "subjectId": "238923",
      "info": "556人关注"
    },
    {
      "cover": "https://cdn.jsdelivr.net/gh/czy0729/Bangumi-Static@master/data/discovery/cover/616.jpg",
      "title": "CLANNAD Original SoundTrack",
      "subjectId": "616",
      "info": "2259人关注"
    }
  ],
  "real": [
    {
      "cover": "https://cdn.jsdelivr.net/gh/czy0729/Bangumi-Static@master/data/discovery/cover/349534.jpg",
      "title": "오징어 게임",
      "subjectId": "349534",
      "info": "175人关注"
    },
    {
      "cover": "https://cdn.jsdelivr.net/gh/czy0729/Bangumi-Static@master/data/discovery/cover/343491.jpg",
      "title": "仮面ライダーリバイス",
      "subjectId": "343491",
      "info": "229人关注"
    },
    {
      "cover": "https://cdn.jsdelivr.net/gh/czy0729/Bangumi-Static@master/data/discovery/cover/334095.jpg",
      "title": "Foundation",
      "subjectId": "334095",
      "info": "36人关注"
    },
    {
      "cover": "https://cdn.jsdelivr.net/gh/czy0729/Bangumi-Static@master/data/discovery/cover/333282.jpg",
      "title": "ウルトラマントリガー NEW GENERATION TIGA",
      "subjectId": "333282",
      "info": "238人关注"
    },
    {
      "cover": "https://cdn.jsdelivr.net/gh/czy0729/Bangumi-Static@master/data/discovery/cover/341262.jpg",
      "title": "Sex Education Season 3",
      "subjectId": "341262",
      "info": "38人关注"
    },
    {
      "cover": "https://cdn.jsdelivr.net/gh/czy0729/Bangumi-Static@master/data/discovery/cover/349623.jpg",
      "title": "消えた初恋",
      "subjectId": "349623",
      "info": "20人关注"
    },
    {
      "cover": "https://cdn.jsdelivr.net/gh/czy0729/Bangumi-Static@master/data/discovery/cover/286617.jpg",
      "title": "今際の国のアリス",
      "subjectId": "286617",
      "info": "260人关注"
    }
  ],
  "today": "今日上映 6 部，共 2436 人收看"
}