{"anime":[{"cover":"https://cdn.jsdelivr.net/gh/czy0729/Bangumi-Static@master/data/discovery/cover/278826.jpg","title":"Re:ゼロから始める異世界生活 2nd season","subjectId":"278826","info":"1786人关注"},{"cover":"https://cdn.jsdelivr.net/gh/czy0729/Bangumi-Static@master/data/discovery/cover/277954.jpg","title":"やはり俺の青春ラブコメはまちがっている。完","subjectId":"277954","info":"2558人关注"},{"cover":"https://cdn.jsdelivr.net/gh/czy0729/Bangumi-Static@master/data/discovery/cover/285813.jpg","title":"GREAT PRETENDER","subjectId":"285813","info":"1730人关注"},{"cover":"https://cdn.jsdelivr.net/gh/czy0729/Bangumi-Static@master/data/discovery/cover/285879.jpg","title":"デカダンス","subjectId":"285879","info":"988人关注"},{"cover":"https://cdn.jsdelivr.net/gh/czy0729/Bangumi-Static@master/data/discovery/cover/292222.jpg","title":"魔王学院の不適合者 ～史上最強の魔王の始祖、転生して子孫たちの学校へ通う～","subjectId":"292222","info":"822人关注"},{"cover":"https://cdn.jsdelivr.net/gh/czy0729/Bangumi-Static@master/data/discovery/cover/292382.jpg","title":"日本沈没2020","subjectId":"292382","info":"1091人关注"},{"cover":"https://cdn.jsdelivr.net/gh/czy0729/Bangumi-Static@master/data/discovery/cover/296076.jpg","title":"彼女、お借りします","subjectId":"296076","info":"974人关注"}],"game":[{"cover":"https://cdn.jsdelivr.net/gh/czy0729/Bangumi-Static@master/data/discovery/cover/297264.jpg","title":"ATRI -My Dear Moments-","subjectId":"297264","info":"936人关注"},{"cover":"https://cdn.jsdelivr.net/gh/czy0729/Bangumi-Static@master/data/discovery/cover/295957.jpg","title":"Summer Pockets -REFLECTION BLUE-","subjectId":"295957","info":"474人关注"},{"cover":"https://cdn.jsdelivr.net/gh/czy0729/Bangumi-Static@master/data/discovery/cover/226254.jpg","title":"ランス10","subjectId":"226254","info":"1373人关注"},{"cover":"https://cdn.jsdelivr.net/gh/czy0729/Bangumi-Static@master/data/discovery/cover/297265.jpg","title":"徒花異譚","subjectId":"297265","info":"319人关注"},{"cover":"https://cdn.jsdelivr.net/gh/czy0729/Bangumi-Static@master/data/discovery/cover/200187.jpg","title":"The Last of Us: Part II","subjectId":"200187","info":"284人关注"},{"cover":"https://cdn.jsdelivr.net/gh/czy0729/Bangumi-Static@master/data/discovery/cover/295320.jpg","title":"美少女万華鏡 -理と迷宮の少女-","subjectId":"295320","info":"885人关注"},{"cover":"https://cdn.jsdelivr.net/gh/czy0729/Bangumi-Static@master/data/discovery/cover/115976.jpg","title":"ピュア×コネクト","subjectId":"115976","info":"473人关注"}],"book":[{"cover":"https://cdn.jsdelivr.net/gh/czy0729/Bangumi-Static@master/data/discovery/cover/268279.jpg","title":"チェンソーマン","subjectId":"268279","info":"778人关注"},{"cover":"https://cdn.jsdelivr.net/gh/czy0729/Bangumi-Static@master/data/discovery/cover/179872.jpg","title":"ファイアパンチ","subjectId":"179872","info":"650人关注"},{"cover":"https://cdn.jsdelivr.net/gh/czy0729/Bangumi-Static@master/data/discovery/cover/135218.jpg","title":"かぐや様は告らせたい～天才たちの恋愛頭脳戦～","subjectId":"135218","info":"1102人关注"},{"cover":"https://cdn.jsdelivr.net/gh/czy0729/Bangumi-Static@master/data/discovery/cover/8491.jpg","title":"進撃の巨人","subjectId":"8491","info":"2124人关注"},{"cover":"https://cdn.jsdelivr.net/gh/czy0729/Bangumi-Static@master/data/discovery/cover/188254.jpg","title":"約束のネバーランド","subjectId":"188254","info":"752人关注"},{"cover":"https://cdn.jsdelivr.net/gh/czy0729/Bangumi-Static@master/data/discovery/cover/168891.jpg","title":"鬼滅の刃","subjectId":"168891","info":"757人关注"},{"cover":"https://cdn.jsdelivr.net/gh/czy0729/Bangumi-Static@master/data/discovery/cover/307954.jpg","title":"あやかしトライアングル","subjectId":"307954","info":"60人关注"}],"music":[{"cover":"https://cdn.jsdelivr.net/gh/czy0729/Bangumi-Static@master/data/discovery/cover/163164.jpg","title":"サクラノ詩 サウンドトラックCD","subjectId":"163164","info":"729人关注"},{"cover":"https://cdn.jsdelivr.net/gh/czy0729/Bangumi-Static@master/data/discovery/cover/305087.jpg","title":"花に亡霊","subjectId":"305087","info":"47人关注"},{"cover":"https://cdn.jsdelivr.net/gh/czy0729/Bangumi-Static@master/data/discovery/cover/616.jpg","title":"CLANNAD Original SoundTrack","subjectId":"616","info":"1919人关注"},{"cover":"https://cdn.jsdelivr.net/gh/czy0729/Bangumi-Static@master/data/discovery/cover/308645.jpg","title":"日本沈没2020 ORIGINAL SOUNDTRACK","subjectId":"308645","info":"19人关注"},{"cover":"https://cdn.jsdelivr.net/gh/czy0729/Bangumi-Static@master/data/discovery/cover/18305.jpg","title":"COWBOY BEBOP SOUNDTRACK 1","subjectId":"18305","info":"555人关注"},{"cover":"https://cdn.jsdelivr.net/gh/czy0729/Bangumi-Static@master/data/discovery/cover/287274.jpg","title":"空の青さを知る人よ","subjectId":"287274","info":"42人关注"},{"cover":"https://cdn.jsdelivr.net/gh/czy0729/Bangumi-Static@master/data/discovery/cover/302520.jpg","title":"TVアニメ「かくしごと」イメージアルバム feat.君は天然色","subjectId":"302520","info":"40人关注"}],"real":[{"cover":"https://cdn.jsdelivr.net/gh/czy0729/Bangumi-Static@master/data/discovery/cover/308919.jpg","title":"隐秘的角落","subjectId":"308919","info":"165人关注"},{"cover":"https://cdn.jsdelivr.net/gh/czy0729/Bangumi-Static@master/data/discovery/cover/304573.jpg","title":"ウルトラマンゼット","subjectId":"304573","info":"58人关注"},{"cover":"https://cdn.jsdelivr.net/gh/czy0729/Bangumi-Static@master/data/discovery/cover/300179.jpg","title":"MIU404","subjectId":"300179","info":"23人关注"},{"cover":"https://cdn.jsdelivr.net/gh/czy0729/Bangumi-Static@master/data/discovery/cover/298442.jpg","title":"BG～身辺警護人～","subjectId":"298442","info":"24人关注"},{"cover":"https://cdn.jsdelivr.net/gh/czy0729/Bangumi-Static@master/data/discovery/cover/298440.jpg","title":"ハケンの品格","subjectId":"298440","info":"18人关注"},{"cover":"https://cdn.jsdelivr.net/gh/czy0729/Bangumi-Static@master/data/discovery/cover/108596.jpg","title":"半沢直樹","subjectId":"108596","info":"183人关注"},{"cover":"https://cdn.jsdelivr.net/gh/czy0729/Bangumi-Static@master/data/discovery/cover/307002.jpg","title":"Agents of S.H.I.E.L.D. (Season 7)","subjectId":"307002","info":"31人关注"}],"today":"今日上映 7 部，共 6074 人收看"}