{
  "data": [
    "动作",
    "角色扮演",
    "冒险",
    "射击",
    "策略",
    "第三人称",
    "独立",
    "文字",
    "模拟",
    "主视角",
    "平台",
    "剧情",
    "解谜",
    "多人",
    "恐怖",
    "格斗",
    "回合制",
    "科幻",
    "音乐",
    "育成",
    "益智",
    "体育",
    "生存",
    "沙箱",
    "开放世界",
    "竞速",
    "竞技",
    "俯视角",
    "即时战略",
    "卡牌",
    "MMO",
    "3D",
    "派对",
    "Roguelike",
    "潜入",
    "VR",
    "体感",
    "健身",
    "塔防",
    "MOBA",
    "建造",
    "弹幕",
    "AR",
    "2D",
    "横版",
    "养成",
    "桌面"
  ],
  "nums": {
    "动作": 934,
    "射击": 344,
    "主视角": 175,
    "音乐": 83,
    "文字": 202,
    "冒险": 654,
    "角色扮演": 854,
    "回合制": 93,
    "剧情": 153,
    "策略": 312,
    "即时战略": 42,
    "竞技": 49,
    "格斗": 95,
    "体育": 70,
    "第三人称": 211,
    "平台": 159,
    "模拟": 197,
    "竞速": 52,
    "开放世界": 53,
    "派对": 27,
    "育成": 83,
    "健身": 9,
    "体感": 10,
    "MMO": 31,
    "俯视角": 43,
    "科幻": 87,
    "潜入": 19,
    "多人": 108,
    "恐怖": 108,
    "2D": 1,
    "益智": 81,
    "解谜": 141,
    "塔防": 9,
    "独立": 203,
    "沙箱": 66,
    "卡牌": 35,
    "生存": 70,
    "MOBA": 8,
    "弹幕": 6,
    "横版": 1,
    "VR": 15,
    "3D": 28,
    "AR": 2,
    "养成": 1,
    "Roguelike": 21,
    "建造": 8,
    "桌面": 1
  }
}