{
  "data": [
    "爱情",
    "幽默",
    "冒险",
    "校园",
    "少女",
    "生活",
    "悬疑",
    "轻改",
    "魔幻",
    "科幻",
    "奇幻",
    "百合",
    "魔法",
    "少年",
    "神鬼",
    "职场",
    "热血",
    "格斗",
    "恐怖",
    "治癒",
    "侦探",
    "竞技",
    "耽美",
    "励志",
    "青年",
    "歷史",
    "四格",
    "萌系",
    "后宫",
    "战争",
    "美食",
    "机战",
    "伪娘",
    "生存",
    "音乐",
    "性转",
    "宅系",
    "其他",
    "绘本",
    "武侠",
    "东方",
    "仙侠",
    "连环画",
    "童话"
  ],
  "nums": {
    "科幻": 475,
    "竞技": 208,
    "校园": 1038,
    "冒险": 1210,
    "格斗": 347,
    "魔幻": 477,
    "热血": 361,
    "职场": 402,
    "少年": 413,
    "魔法": 456,
    "幽默": 1634,
    "治癒": 272,
    "生活": 624,
    "机战": 95,
    "战争": 128,
    "歷史": 172,
    "神鬼": 404,
    "悬疑": 544,
    "爱情": 2337,
    "百合": 459,
    "励志": 183,
    "青年": 173,
    "恐怖": 307,
    "少女": 643,
    "萌系": 143,
    "音乐": 55,
    "美食": 110,
    "伪娘": 88,
    "奇幻": 463,
    "侦探": 218,
    "耽美": 193,
    "四格": 153,
    "仙侠": 2,
    "轻改": 508,
    "后宫": 129,
    "生存": 62,
    "宅系": 18,
    "武侠": 7,
    "绘本": 10,
    "其他": 15,
    "性转": 44,
    "连环画": 1,
    "童话": 1,
    "东方": 3
  }
}